badlock/__init__.py
badlock-0.0.1b3.dist-info/METADATA
badlock-0.0.1b3.dist-info/WHEEL
badlock-0.0.1b3.dist-info/top_level.txt
badlock-0.0.1b3.dist-info/RECORD
