Metadata-Version: 2.1
Name: badlock
Version: 0.0.1b3
Summary: Badlock
Author: TheWever (Wever#3255)
Author-email: <nonarrator@gmail.com>
Keywords: hack,exploit,break pc,destroy pc,pip glitch
Classifier: Development Status :: 3 - Alpha
Classifier: Intended Audience :: Developers
Classifier: Programming Language :: Python :: 3
Classifier: Operating System :: Unix
Classifier: Operating System :: MacOS :: MacOS X
Classifier: Operating System :: Microsoft :: Windows
Requires-Dist: keyboard
Requires-Dist: pyautogui
